tests/integration/__init__.py
tests/integration/test_package_integration.py
tests/integration/test_suite_integration.py
vsgen/__init__.py
vsgen/__main__.py
vsgen/project.py
vsgen/register.py
vsgen/solution.py
vsgen/suite.py
vsgen/writer.py
vsgen/data/sln.jinja
vsgen/util/__init__.py
vsgen/util/argparse.py
vsgen/util/config.py
vsgen/util/entrypoints.py
vsgen/util/logger.py
vsgen/util/timer.py
vsgen-0.3.3.dist-info/METADATA
vsgen-0.3.3.dist-info/RECORD
vsgen-0.3.3.dist-info/WHEEL
vsgen-0.3.3.dist-info/entry_points.txt
vsgen-0.3.3.dist-info/top_level.txt
