Metadata-Version: 2.1
Name: vsgen
Version: 0.3.3
Summary: A Microsoft Visual Studio solution and project generator pyackage.
Home-page: https://github.com/dbarsam/python-vsgen
Author: dbarsam
Author-email: dbarsam@gmail.com
License: MIT
Keywords: visual studio project generation
Platform: UNKNOWN
Classifier: Development Status :: 4 - Beta
Classifier: Environment :: Console
Classifier: Intended Audience :: Developers
Classifier: Topic :: Software Development 
Classifier: License :: OSI Approved :: MIT License
Classifier: Programming Language :: Python :: 2.7
Classifier: Programming Language :: Python :: 3.6
Classifier: Topic :: Office/Business :: Groupware
Requires-Python: >=2.7,!=3.0.*,!=3.1.*,!=3.2.*,!=3.3.*
Requires-Dist: jinja2
Requires-Dist: configparser
